[
  {
    "name": "IT-Brindisi",
    "code": "10Y1001A1001A699",
    "key": "1",
    "is_available": true
  },
  {
    "name": "IT-Calabria",
    "code": "10Y1001C--00096J",
    "key": "2",
    "is_available": true
  },
  {
    "name": "IT-Centre-North",
    "code": "10Y1001A1001A70O",
    "key": "3",
    "is_available": true
  },
  {
    "name": "IT-Centre-South",
    "code": "10Y1001A1001A71M",
    "key": "4",
    "is_available": true
  },
  {
    "name": "IT-Foggia",
    "code": "10Y1001A1001A72K",
    "key": "5",
    "is_available": true
  },
  {
    "name": "IT-North",
    "code": "10Y1001A1001A73I",
    "key": "6",
    "is_available": true
  },
  {
    "name": "IT-Priolo",
    "code": "10Y1001A1001A76C",
    "key": "7",
    "is_available": true
  },
  {
    "name": "IT-Rossano",
    "code": "10Y1001A1001A77A",
    "key": "8",
    "is_available": true
  },
  {
    "name": "IT-Sardinia",
    "code": "10Y1001A1001A74G",
    "key": "9",
    "is_available": true
  },
  {
    "name": "IT-Sicily",
    "code": "10Y1001A1001A75E",
    "key": "10",
    "is_available": true
  },
  {
    "name": "IT-South",
    "code": "10Y1001A1001A788",
    "key": "11",
    "is_available": true
  }
]