{"data_mtime":1710247454,"dep_lines":[4,1,2,3,5,6,1,1],"dep_prios":[5,10,5,5,5,5,5,30],"dependencies":["collections.abc","sys","types","_typeshed","typing","typing_extensions","builtins","abc"],"hash":"3e578ac127522cae1551769c4659f088f2f2573102c341911cfe1730e4b75214","id":"functools","ignore_all":true,"interface_hash":"bf28b23bcf4f422796abdc37e6ab146d5a62f03f9a41211f8338d46ada9cd5e4","mtime":1710247382,"options":{"allow_redefinition":false,"allow_untyped_globals":false,"always_false":[],"always_true":[],"bazel":false,"check_untyped_defs":false,"disable_bytearray_promotion":false,"disable_error_code":[],"disable_memoryview_promotion":false,"disabled_error_codes":[],"disallow_any_decorated":false,"disallow_any_explicit":false,"disallow_any_expr":false,"disallow_any_generics":false,"disallow_any_unimported":false,"disallow_incomplete_defs":false,"disallow_subclassing_any":false,"disallow_untyped_calls":false,"disallow_untyped_decorators":false,"disallow_untyped_defs":false,"enable_error_code":[],"enabled_error_codes":[],"extra_checks":false,"follow_imports":"normal","follow_imports_for_stubs":false,"ignore_errors":false,"ignore_missing_imports":false,"implicit_optional":false,"implicit_reexport":true,"local_partial_types":false,"mypyc":false,"old_type_inference":false,"platform":"linux","plugins":[],"strict_concatenate":false,"strict_equality":false,"strict_optional":true,"warn_no_return":true,"warn_return_any":false,"warn_unreachable":false,"warn_unused_ignores":false},"path":"/home/eddie/EW/edwh-bundler-plugin/venv/lib/python3.10/site-packages/mypy/typeshed/stdlib/functools.pyi","plugin_data":null,"size":7334,"suppressed":[],"version_id":"1.9.0"}